intel_extension_for_tensorflow/libintel_xla.so
intel_extension_for_tensorflow/libitex_common.so
intel_extension_for_tensorflow/libitex_gpu_internal.so
intel_extension_for_tensorflow/libitex_gpu_xetla.so
intel_extension_for_tensorflow/python/_pywrap_itex.so
intel_extension_for_tensorflow_lib/__init__.py
intel_extension_for_tensorflow_lib/third-party-programs/THIRD-PARTY-PROGRAMS
intel_extension_for_tensorflow_lib/third-party-programs/third-party-programs-of-onednn.txt
intel_extension_for_tensorflow_lib/third-party-programs/third-party-programs-of-onevpl.txt
tensorflow-plugins/libitex_gpu.so
intel_extension_for_tensorflow_lib-2.15.0.3.2.dist-info/LICENSE.txt
intel_extension_for_tensorflow_lib-2.15.0.3.2.dist-info/METADATA
intel_extension_for_tensorflow_lib-2.15.0.3.2.dist-info/WHEEL
intel_extension_for_tensorflow_lib-2.15.0.3.2.dist-info/top_level.txt
intel_extension_for_tensorflow_lib-2.15.0.3.2.dist-info/RECORD
