Metadata-Version: 2.2
Name: intel_extension_for_tensorflow_lib
Version: 2.15.0.3.2
Summary: Intel® Extension for Tensorflow* library
Home-page: https://github.com/intel/intel-extension-for-tensorflow
Download-URL: https://github.com/intel/intel-extension-for-tensorflow/tags
Author: Intel Corporation
Author-email: itex.maintainers@intel.com
License: Apache 2.0
Project-URL: Bug Tracker, https://github.com/intel/intel-extension-for-tensorflow/issues
Keywords: Intel® Extension for Tensorflow*
Classifier: Development Status :: 5 - Production/Stable
Classifier: Intended Audience :: Developers
Classifier: Intended Audience :: Education
Classifier: Intended Audience :: Science/Research
Classifier: License :: OSI Approved :: Apache Software License
Classifier: Programming Language :: Python :: 3.9
Classifier: Programming Language :: Python :: 3.10
Classifier: Programming Language :: Python :: 3.11
Classifier: Topic :: Scientific/Engineering
Classifier: Topic :: Scientific/Engineering :: Mathematics
Classifier: Topic :: Scientific/Engineering :: Artificial Intelligence
Classifier: Topic :: Software Development
Classifier: Topic :: Software Development :: Libraries
Classifier: Topic :: Software Development :: Libraries :: Python Modules
Requires-Python: >=3.9
License-File: LICENSE.txt
Requires-Dist: grpcio>=1.8.6
Requires-Dist: wheel
Dynamic: author
Dynamic: author-email
Dynamic: classifier
Dynamic: description
Dynamic: description-content-type
Dynamic: download-url
Dynamic: home-page
Dynamic: keywords
Dynamic: license
Dynamic: project-url
Dynamic: requires-dist
Dynamic: requires-python
Dynamic: summary
